tkinter_gl/__init__.py
tkinter_gl/tk/README
tkinter_gl/tk/license.terms
tkinter_gl/tk/darwin/Tkgl1.0/libTkgl1.0.dylib
tkinter_gl/tk/darwin/Tkgl1.0/libtcl9Tkgl1.0.dylib
tkinter_gl/tk/darwin/Tkgl1.0/pkgIndex.tcl
tkinter_gl/tk/darwin/Tkgl1.1/libTkgl1.1.dylib
tkinter_gl/tk/darwin/Tkgl1.1/libtcl9Tkgl1.1.dylib
tkinter_gl/tk/darwin/Tkgl1.1/pkgIndex.tcl
tkinter_gl/tk/linux/Tkgl1.0/libTkgl1.0.so
tkinter_gl/tk/linux/Tkgl1.0/libtcl9Tkgl1.0.so
tkinter_gl/tk/linux/Tkgl1.0/pkgIndex.tcl
tkinter_gl/tk/linux/Tkgl1.1/libTkgl1.1.so
tkinter_gl/tk/linux/Tkgl1.1/libtcl9Tkgl1.1.so
tkinter_gl/tk/linux/Tkgl1.1/pkgIndex.tcl
tkinter_gl/tk/win32/TkGL1.0/Tkgl10t.dll
tkinter_gl/tk/win32/TkGL1.0/Tkgl10t.lib
tkinter_gl/tk/win32/TkGL1.0/pkgIndex.tcl
tkinter_gl/tk/win32/TkGL1.0/tcl9Tkgl10.dll
tkinter_gl/tk/win32/TkGL1.0/tcl9Tkgl10.lib
tkinter_gl/tk/win32/TkGL1.1/Tkgl11t.dll
tkinter_gl/tk/win32/TkGL1.1/Tkgl11t.lib
tkinter_gl/tk/win32/TkGL1.1/pkgIndex.tcl
tkinter_gl/tk/win32/TkGL1.1/tcl9Tkgl11.dll
tkinter_gl/tk/win32/TkGL1.1/tcl9Tkgl11.lib
tkinter_gl-1.0a4.dist-info/LICENSE
tkinter_gl-1.0a4.dist-info/METADATA
tkinter_gl-1.0a4.dist-info/WHEEL
tkinter_gl-1.0a4.dist-info/top_level.txt
tkinter_gl-1.0a4.dist-info/RECORD
